running_analyzer/__init__.py
running_analyzer/__main__.py
running_analyzer/cli.py
running_analyzer/db.py
running_analyzer/models.py
running_analyzer/utils.py
running_analyzer-0.1.0.dist-info/METADATA
running_analyzer-0.1.0.dist-info/WHEEL
running_analyzer-0.1.0.dist-info/entry_points.txt
running_analyzer-0.1.0.dist-info/licenses/LICENSE
running_analyzer-0.1.0.dist-info/RECORD
