Metadata-Version: 2.4
Name: running-analyzer
Version: 0.1.0
Summary: A CLI tool to analyze running data
License-File: LICENSE
Requires-Python: >=3.13
Requires-Dist: alembic>=1.14.1
Requires-Dist: annotated-types>=0.7.0
Requires-Dist: cfgv>=3.4.0
Requires-Dist: click>=8.1.8
Requires-Dist: distlib>=0.3.9
Requires-Dist: filelock>=3.17.0
Requires-Dist: fitparse>=1.2.0
Requires-Dist: identify>=2.6.7
Requires-Dist: markdown-it-py>=3.0.0
Requires-Dist: mdurl>=0.1.2
Requires-Dist: nodeenv>=1.9.1
Requires-Dist: numpy>=2.2.3
Requires-Dist: platformdirs>=4.3.6
Requires-Dist: plotext>=5.3.2
Requires-Dist: pre-commit>=4.1.0
Requires-Dist: psycopg2>=2.9.10
Requires-Dist: pydantic-core>=2.27.2
Requires-Dist: pydantic>=2.10.6
Requires-Dist: pygments>=2.19.1
Requires-Dist: python-decouple>=3.8
Requires-Dist: pyyaml>=6.0.2
Requires-Dist: rich>=13.9.4
Requires-Dist: ruff>=0.9.6
Requires-Dist: shellingham>=1.5.4
Requires-Dist: sqlalchemy>=2.0.38
Requires-Dist: sqlmodel>=0.0.22
Requires-Dist: typer>=0.15.1
Requires-Dist: typing-extensions>=4.12.2
Requires-Dist: virtualenv>=20.29.2
